{
  "name": "Thuận Nè",
  "ID": "100040305616096",
  "mainROD": "𝖀𝖓𝖐𝖓𝖔𝖜𝖓 𝕿𝖗𝖎𝖉𝖊𝖓𝖙",
  "GPS": {
    "locate": "The Crater",
    "area": "Crater Edge – The Void"
  },
  "fishBag": [
    {
      "ID": 16,
      "name": "Arctic Ray",
      "category": "Uncommon",
      "size": 120,
      "sell": 990,
      "image": "https://i.imgur.com/fJwcFHQ.png"
    },
    {
      "ID": 17,
      "name": "Boomerang",
      "category": "Common",
      "size": 31,
      "sell": 200,
      "image": "https://i.imgur.com/dtBM9sP.png"
    },
    {
      "ID": 18,
      "name": "Pengwing",
      "category": "Uncommon",
      "size": 32,
      "sell": 220,
      "image": "https://i.imgur.com/dH8XB25.png"
    },
    {
      "ID": 20,
      "name": "Pinnacarid",
      "category": "Uncommon",
      "size": 54,
      "sell": 480,
      "image": "https://i.imgur.com/pbOeb3U.png"
    },
    {
      "ID": 21,
      "name": "Arctic Ray",
      "category": "Uncommon",
      "size": 120,
      "sell": 990,
      "image": "https://i.imgur.com/fJwcFHQ.png"
    },
    {
      "ID": 22,
      "name": "Arctic Peeper",
      "category": "Common",
      "size": 34,
      "sell": 200,
      "image": "https://i.imgur.com/Qsx7khe.png"
    },
    {
      "ID": 23,
      "name": "Glow Whale",
      "category": "Epic",
      "size": 30,
      "sell": 15120,
      "image": "https://i.imgur.com/DkQGFvG.png"
    },
    {
      "ID": 24,
      "name": "Pinnacarid",
      "category": "Uncommon",
      "size": 54,
      "sell": 480,
      "image": "https://i.imgur.com/pbOeb3U.png"
    },
    {
      "ID": 25,
      "name": "Arctic Peeper",
      "category": "Common",
      "size": 34,
      "sell": 200,
      "image": "https://i.imgur.com/Qsx7khe.png"
    },
    {
      "ID": 26,
      "name": "Arctic Peeper",
      "category": "Common",
      "size": 34,
      "sell": 200,
      "image": "https://i.imgur.com/Qsx7khe.png"
    },
    {
      "ID": 27,
      "name": "Bladderfish",
      "category": "Common",
      "size": 32,
      "sell": 200,
      "image": "https://i.imgur.com/W5IegiJ.png"
    },
    {
      "ID": 28,
      "name": "Rockgrub",
      "category": "Epic",
      "size": 24,
      "sell": 1180,
      "image": "https://i.imgur.com/xbdLdm4.jpg"
    },
    {
      "ID": 29,
      "name": "Boomerang",
      "category": "Common",
      "size": 31,
      "sell": 200,
      "image": "https://i.imgur.com/dtBM9sP.png"
    },
    {
      "ID": 30,
      "name": "Bladderfish",
      "category": "Common",
      "size": 32,
      "sell": 200,
      "image": "https://i.imgur.com/W5IegiJ.png"
    },
    {
      "ID": 31,
      "name": "Pengling",
      "category": "Uncommon",
      "size": 63,
      "sell": 650,
      "image": "https://i.imgur.com/Qy0kJT5.png"
    },
    {
      "ID": 32,
      "name": "Pengling",
      "category": "Uncommon",
      "size": 63,
      "sell": 650,
      "image": "https://i.imgur.com/Qy0kJT5.png"
    },
    {
      "ID": 33,
      "name": "Pengling",
      "category": "Uncommon",
      "size": 63,
      "sell": 650,
      "image": "https://i.imgur.com/Qy0kJT5.png"
    },
    {
      "ID": 34,
      "name": "Pengwing",
      "category": "Uncommon",
      "size": 32,
      "sell": 220,
      "image": "https://i.imgur.com/dH8XB25.png"
    },
    {
      "ID": 35,
      "name": "Arctic Ray",
      "category": "Uncommon",
      "size": 120,
      "sell": 990,
      "image": "https://i.imgur.com/fJwcFHQ.png"
    },
    {
      "ID": 36,
      "name": "Arctic Ray",
      "category": "Uncommon",
      "size": 120,
      "sell": 990,
      "image": "https://i.imgur.com/fJwcFHQ.png"
    },
    {
      "ID": 37,
      "name": "Arctic Ray",
      "category": "Uncommon",
      "size": 120,
      "sell": 990,
      "image": "https://i.imgur.com/fJwcFHQ.png"
    },
    {
      "ID": 38,
      "name": "Rockgrub",
      "category": "Epic",
      "size": 24,
      "sell": 1180,
      "image": "https://i.imgur.com/xbdLdm4.jpg"
    },
    {
      "ID": 39,
      "name": "Titan Holefish",
      "category": "Epic",
      "size": 450,
      "sell": 8690,
      "image": "https://i.imgur.com/2uJIRkL.png"
    },
    {
      "ID": 40,
      "name": "Bladderfish",
      "category": "Common",
      "size": 32,
      "sell": 200,
      "image": "https://i.imgur.com/W5IegiJ.png"
    },
    {
      "ID": 41,
      "name": "Glow Whale",
      "category": "Epic",
      "size": 30,
      "sell": 15120,
      "image": "https://i.imgur.com/DkQGFvG.png"
    },
    {
      "ID": 42,
      "name": "Pengwing",
      "category": "Uncommon",
      "size": 32,
      "sell": 220,
      "image": "https://i.imgur.com/dH8XB25.png"
    },
    {
      "ID": 43,
      "name": "Bladderfish",
      "category": "Common",
      "size": 32,
      "sell": 200,
      "image": "https://i.imgur.com/W5IegiJ.png"
    },
    {
      "ID": 44,
      "name": "Boomerang",
      "category": "Common",
      "size": 31,
      "sell": 200,
      "image": "https://i.imgur.com/dtBM9sP.png"
    },
    {
      "ID": 45,
      "name": "Bladderfish",
      "category": "Common",
      "size": 32,
      "sell": 200,
      "image": "https://i.imgur.com/W5IegiJ.png"
    },
    {
      "ID": 47,
      "name": "Arctic Peeper",
      "category": "Common",
      "size": 34,
      "sell": 200,
      "image": "https://i.imgur.com/Qsx7khe.png"
    },
    {
      "ID": 48,
      "name": "Pinnacarid",
      "category": "Uncommon",
      "size": 54,
      "sell": 480,
      "image": "https://i.imgur.com/pbOeb3U.png"
    },
    {
      "ID": 49,
      "name": "Pengwing",
      "category": "Uncommon",
      "size": 32,
      "sell": 220,
      "image": "https://i.imgur.com/dH8XB25.png"
    },
    {
      "ID": 50,
      "name": "Titan Holefish",
      "category": "Epic",
      "size": 450,
      "sell": 8690,
      "image": "https://i.imgur.com/2uJIRkL.png"
    },
    {
      "ID": 51,
      "name": "Titan Holefish",
      "category": "Epic",
      "size": 450,
      "sell": 8690,
      "image": "https://i.imgur.com/2uJIRkL.png"
    },
    {
      "ID": 52,
      "name": "Pengling",
      "category": "Uncommon",
      "size": 63,
      "sell": 650,
      "image": "https://i.imgur.com/Qy0kJT5.png"
    },
    {
      "ID": 53,
      "name": "Bladderfish",
      "category": "Common",
      "size": 32,
      "sell": 200,
      "image": "https://i.imgur.com/W5IegiJ.png"
    },
    {
      "ID": 54,
      "name": "Arctic Ray",
      "category": "Uncommon",
      "size": 120,
      "sell": 990,
      "image": "https://i.imgur.com/fJwcFHQ.png"
    },
    {
      "ID": 55,
      "name": "Pinnacarid",
      "category": "Uncommon",
      "size": 54,
      "sell": 480,
      "image": "https://i.imgur.com/pbOeb3U.png"
    },
    {
      "ID": 56,
      "name": "Boomerang",
      "category": "Common",
      "size": 31,
      "sell": 200,
      "image": "https://i.imgur.com/dtBM9sP.png"
    },
    {
      "ID": 57,
      "name": "Arctic Peeper",
      "category": "Common",
      "size": 34,
      "sell": 200,
      "image": "https://i.imgur.com/Qsx7khe.png"
    },
    {
      "ID": 58,
      "name": "Arctic Peeper",
      "category": "Common",
      "size": 34,
      "sell": 200,
      "image": "https://i.imgur.com/Qsx7khe.png"
    },
    {
      "ID": 59,
      "name": "Pengwing",
      "category": "Uncommon",
      "size": 32,
      "sell": 220,
      "image": "https://i.imgur.com/dH8XB25.png"
    },
    {
      "ID": 60,
      "name": "Arctic Peeper",
      "category": "Common",
      "size": 34,
      "sell": 200,
      "image": "https://i.imgur.com/Qsx7khe.png"
    },
    {
      "ID": 61,
      "name": "Boomerang",
      "category": "Common",
      "size": 31,
      "sell": 200,
      "image": "https://i.imgur.com/dtBM9sP.png"
    },
    {
      "ID": 62,
      "name": "Glow Whale",
      "category": "Epic",
      "size": 30,
      "sell": 15120,
      "image": "https://i.imgur.com/DkQGFvG.png"
    },
    {
      "ID": 63,
      "name": "Arctic Ray",
      "category": "Uncommon",
      "size": 120,
      "sell": 990,
      "image": "https://i.imgur.com/fJwcFHQ.png"
    },
    {
      "ID": 64,
      "name": "Pinnacarid",
      "category": "Uncommon",
      "size": 54,
      "sell": 480,
      "image": "https://i.imgur.com/pbOeb3U.png"
    },
    {
      "ID": 65,
      "name": "Titan Holefish",
      "category": "Epic",
      "size": 450,
      "sell": 8690,
      "image": "https://i.imgur.com/2uJIRkL.png"
    },
    {
      "ID": 66,
      "name": "Arctic Peeper",
      "category": "Common",
      "size": 34,
      "sell": 200,
      "image": "https://i.imgur.com/Qsx7khe.png"
    },
    {
      "ID": 67,
      "name": "Arctic Peeper",
      "category": "Common",
      "size": 34,
      "sell": 200,
      "image": "https://i.imgur.com/Qsx7khe.png"
    },
    {
      "ID": 68,
      "name": "Arctic Peeper",
      "category": "Common",
      "size": 34,
      "sell": 200,
      "image": "https://i.imgur.com/Qsx7khe.png"
    },
    {
      "ID": 69,
      "name": "Titan Holefish",
      "category": "Epic",
      "size": 450,
      "sell": 8690,
      "image": "https://i.imgur.com/2uJIRkL.png"
    },
    {
      "ID": 70,
      "name": "Pinnacarid",
      "category": "Uncommon",
      "size": 54,
      "sell": 480,
      "image": "https://i.imgur.com/pbOeb3U.png"
    },
    {
      "ID": 71,
      "name": "Chelicerate",
      "category": "Legendary",
      "size": 5500,
      "sell": 876500,
      "image": "https://i.imgur.com/PaeEsyM.png"
    },
    {
      "ID": 72,
      "name": "Arctic Ray",
      "category": "Uncommon",
      "size": 120,
      "sell": 990,
      "image": "https://i.imgur.com/fJwcFHQ.png"
    },
    {
      "ID": 73,
      "name": "Bladderfish",
      "category": "Common",
      "size": 32,
      "sell": 200,
      "image": "https://i.imgur.com/W5IegiJ.png"
    },
    {
      "ID": 74,
      "name": "Chelicerate",
      "category": "Legendary",
      "size": 5500,
      "sell": 876500,
      "image": "https://i.imgur.com/PaeEsyM.png"
    },
    {
      "ID": 75,
      "name": "Glow Whale",
      "category": "Epic",
      "size": 30,
      "sell": 15120,
      "image": "https://i.imgur.com/DkQGFvG.png"
    },
    {
      "ID": 76,
      "name": "Titan Holefish",
      "category": "Epic",
      "size": 450,
      "sell": 8690,
      "image": "https://i.imgur.com/2uJIRkL.png"
    },
    {
      "ID": 77,
      "name": "Pengwing",
      "category": "Uncommon",
      "size": 32,
      "sell": 220,
      "image": "https://i.imgur.com/dH8XB25.png"
    },
    {
      "ID": 78,
      "name": "Rockgrub",
      "category": "Epic",
      "size": 24,
      "sell": 1180,
      "image": "https://i.imgur.com/xbdLdm4.jpg"
    },
    {
      "ID": 79,
      "name": "Arctic Ray",
      "category": "Uncommon",
      "size": 120,
      "sell": 990,
      "image": "https://i.imgur.com/fJwcFHQ.png"
    },
    {
      "ID": 80,
      "name": "Glow Whale",
      "category": "Epic",
      "size": 30,
      "sell": 15120,
      "image": "https://i.imgur.com/DkQGFvG.png"
    },
    {
      "ID": 81,
      "name": "Boomerang",
      "category": "Common",
      "size": 31,
      "sell": 200,
      "image": "https://i.imgur.com/dtBM9sP.png"
    },
    {
      "ID": 82,
      "name": "Boomerang",
      "category": "Common",
      "size": 31,
      "sell": 200,
      "image": "https://i.imgur.com/dtBM9sP.png"
    },
    {
      "ID": 83,
      "name": "Glow Whale",
      "category": "Epic",
      "size": 30,
      "sell": 15120,
      "image": "https://i.imgur.com/DkQGFvG.png"
    },
    {
      "ID": 84,
      "name": "Rockgrub",
      "category": "Epic",
      "size": 24,
      "sell": 1180,
      "image": "https://i.imgur.com/xbdLdm4.jpg"
    },
    {
      "ID": 85,
      "name": "Pengwing",
      "category": "Uncommon",
      "size": 32,
      "sell": 220,
      "image": "https://i.imgur.com/dH8XB25.png"
    },
    {
      "ID": 86,
      "name": "Arctic Ray",
      "category": "Uncommon",
      "size": 120,
      "sell": 990,
      "image": "https://i.imgur.com/fJwcFHQ.png"
    },
    {
      "ID": 87,
      "name": "Pengwing",
      "category": "Uncommon",
      "size": 32,
      "sell": 220,
      "image": "https://i.imgur.com/dH8XB25.png"
    },
    {
      "ID": 88,
      "name": "Pinnacarid",
      "category": "Uncommon",
      "size": 54,
      "sell": 480,
      "image": "https://i.imgur.com/pbOeb3U.png"
    },
    {
      "ID": 89,
      "name": "Arctic Peeper",
      "category": "Common",
      "size": 34,
      "sell": 200,
      "image": "https://i.imgur.com/Qsx7khe.png"
    },
    {
      "ID": 90,
      "name": "Boomerang",
      "category": "Common",
      "size": 31,
      "sell": 200,
      "image": "https://i.imgur.com/dtBM9sP.png"
    },
    {
      "ID": 91,
      "name": "Boomerang",
      "category": "Common",
      "size": 31,
      "sell": 200,
      "image": "https://i.imgur.com/dtBM9sP.png"
    },
    {
      "ID": 92,
      "name": "Void Chelicerate",
      "category": "Legendary",
      "size": 6500,
      "sell": 1107080,
      "image": "https://i.imgur.com/VuLnzT8.png"
    },
    {
      "ID": 93,
      "name": "Void Chelicerate",
      "category": "Legendary",
      "size": 6500,
      "sell": 1107080,
      "image": "https://i.imgur.com/VuLnzT8.png"
    },
    {
      "ID": 94,
      "name": "Void Chelicerate",
      "category": "Legendary",
      "size": 6500,
      "sell": 1107080,
      "image": "https://i.imgur.com/VuLnzT8.png"
    },
    {
      "ID": 95,
      "name": "Void Chelicerate",
      "category": "Legendary",
      "size": 6500,
      "sell": 1107080,
      "image": "https://i.imgur.com/VuLnzT8.png"
    },
    {
      "ID": 96,
      "name": "Hoopfish",
      "category": "Common",
      "size": 27,
      "sell": 190,
      "image": "https://i.imgur.com/1I7IeiH.png"
    },
    {
      "ID": 97,
      "name": "Bladderfish",
      "category": "Common",
      "size": 32,
      "sell": 200,
      "image": "https://i.imgur.com/W5IegiJ.png"
    },
    {
      "ID": 98,
      "name": "Arctic Ray",
      "category": "Uncommon",
      "size": 120,
      "sell": 990,
      "image": "https://i.imgur.com/fJwcFHQ.png"
    },
    {
      "ID": 99,
      "name": "Boomerang",
      "category": "Common",
      "size": 31,
      "sell": 200,
      "image": "https://i.imgur.com/dtBM9sP.png"
    },
    {
      "ID": 100,
      "name": "Arctic Peeper",
      "category": "Common",
      "size": 34,
      "sell": 200,
      "image": "https://i.imgur.com/Qsx7khe.png"
    },
    {
      "ID": 101,
      "name": "Boomerang",
      "category": "Common",
      "size": 31,
      "sell": 200,
      "image": "https://i.imgur.com/dtBM9sP.png"
    },
    {
      "ID": 102,
      "name": "Boomerang",
      "category": "Common",
      "size": 31,
      "sell": 200,
      "image": "https://i.imgur.com/dtBM9sP.png"
    },
    {
      "ID": 103,
      "name": "Arctic Ray",
      "category": "Uncommon",
      "size": 120,
      "sell": 990,
      "image": "https://i.imgur.com/fJwcFHQ.png"
    },
    {
      "ID": 104,
      "name": "Arctic Ray",
      "category": "Uncommon",
      "size": 120,
      "sell": 990,
      "image": "https://i.imgur.com/fJwcFHQ.png"
    },
    {
      "ID": 105,
      "name": "Bladderfish",
      "category": "Common",
      "size": 32,
      "sell": 200,
      "image": "https://i.imgur.com/W5IegiJ.png"
    },
    {
      "ID": 106,
      "name": "Ghost Leviathan Juvenile",
      "category": "Legendary",
      "size": 6700,
      "sell": 720500,
      "image": "https://i.imgur.com/R4SDc8k.jpg"
    },
    {
      "ID": 107,
      "name": "Ghost Leviathan Juvenile",
      "category": "Legendary",
      "size": 6700,
      "sell": 720500,
      "image": "https://i.imgur.com/R4SDc8k.jpg"
    },
    {
      "ID": 108,
      "name": "Ghost Leviathan Juvenile",
      "category": "Legendary",
      "size": 6700,
      "sell": 720500,
      "image": "https://i.imgur.com/R4SDc8k.jpg"
    },
    {
      "ID": 109,
      "name": "Ghost Leviathan Juvenile",
      "category": "Legendary",
      "size": 6700,
      "sell": 720500,
      "image": "https://i.imgur.com/R4SDc8k.jpg"
    },
    {
      "ID": 110,
      "name": "Grand Demon Leviathan",
      "category": "Mythical",
      "size": 37300,
      "sell": 35345800,
      "image": "https://i.imgur.com/WuWQOYy.jpg"
    },
    {
      "ID": 111,
      "name": "Ghost Leviathan Juvenile",
      "category": "Legendary",
      "size": 6700,
      "sell": 720500,
      "image": "https://i.imgur.com/R4SDc8k.jpg"
    },
    {
      "ID": 112,
      "name": "Red Eyeye",
      "category": "Common",
      "size": 36,
      "sell": 230,
      "image": "https://i.imgur.com/5CynMOd.png"
    },
    {
      "ID": 113,
      "name": "Crimson Ray",
      "category": "Uncommon",
      "size": 300,
      "sell": 100,
      "image": "https://i.imgur.com/ii63Q5r.png"
    },
    {
      "ID": 114,
      "name": "Magmarang",
      "category": "Common",
      "size": 33,
      "sell": 210,
      "image": "https://i.imgur.com/0bOcIwM.png"
    },
    {
      "ID": 115,
      "name": "Sea Dragon Leviathan",
      "category": "Legendary",
      "size": 11000,
      "sell": 1580000,
      "image": "https://i.imgur.com/iALri8R.png"
    },
    {
      "ID": 116,
      "name": "Warper",
      "category": "Epic",
      "size": 170,
      "sell": 3480,
      "image": "https://i.imgur.com/XRsxfIV.png"
    },
    {
      "ID": 117,
      "name": "Lava Larva",
      "category": "Uncommon",
      "size": 24,
      "sell": 410,
      "image": "https://i.imgur.com/DEhFwIb.png"
    },
    {
      "ID": 118,
      "name": "Lava Larva",
      "category": "Uncommon",
      "size": 24,
      "sell": 410,
      "image": "https://i.imgur.com/DEhFwIb.png"
    },
    {
      "ID": 119,
      "name": "Red Eyeye",
      "category": "Common",
      "size": 36,
      "sell": 230,
      "image": "https://i.imgur.com/5CynMOd.png"
    },
    {
      "ID": 120,
      "name": "Lava Lizard",
      "category": "Rare",
      "size": 870,
      "sell": 3850,
      "image": "https://i.imgur.com/AblidWp.png"
    },
    {
      "ID": 121,
      "name": "Lava Lizard",
      "category": "Rare",
      "size": 870,
      "sell": 3850,
      "image": "https://i.imgur.com/AblidWp.png"
    },
    {
      "ID": 122,
      "name": "Red Eyeye",
      "category": "Common",
      "size": 36,
      "sell": 230,
      "image": "https://i.imgur.com/5CynMOd.png"
    },
    {
      "ID": 123,
      "name": "Crimson Ray",
      "category": "Uncommon",
      "size": 300,
      "sell": 100,
      "image": "https://i.imgur.com/ii63Q5r.png"
    },
    {
      "ID": 124,
      "name": "Crimson Ray",
      "category": "Uncommon",
      "size": 300,
      "sell": 100,
      "image": "https://i.imgur.com/ii63Q5r.png"
    },
    {
      "ID": 125,
      "name": "Magmarang",
      "category": "Common",
      "size": 33,
      "sell": 210,
      "image": "https://i.imgur.com/0bOcIwM.png"
    },
    {
      "ID": 126,
      "name": "Lava Lizard",
      "category": "Rare",
      "size": 870,
      "sell": 3850,
      "image": "https://i.imgur.com/AblidWp.png"
    },
    {
      "ID": 127,
      "name": "Lava Lizard",
      "category": "Rare",
      "size": 870,
      "sell": 3850,
      "image": "https://i.imgur.com/AblidWp.png"
    },
    {
      "ID": 128,
      "name": "Warper",
      "category": "Epic",
      "size": 170,
      "sell": 3480,
      "image": "https://i.imgur.com/XRsxfIV.png"
    },
    {
      "ID": 129,
      "name": "Lava Larva",
      "category": "Uncommon",
      "size": 24,
      "sell": 410,
      "image": "https://i.imgur.com/DEhFwIb.png"
    },
    {
      "ID": 130,
      "name": "Magmarang",
      "category": "Common",
      "size": 33,
      "sell": 210,
      "image": "https://i.imgur.com/0bOcIwM.png"
    },
    {
      "ID": 131,
      "name": "Magmarang",
      "category": "Common",
      "size": 33,
      "sell": 210,
      "image": "https://i.imgur.com/0bOcIwM.png"
    },
    {
      "ID": 132,
      "name": "Lava Lizard",
      "category": "Rare",
      "size": 870,
      "sell": 3850,
      "image": "https://i.imgur.com/AblidWp.png"
    },
    {
      "ID": 133,
      "name": "Red Eyeye",
      "category": "Common",
      "size": 36,
      "sell": 230,
      "image": "https://i.imgur.com/5CynMOd.png"
    },
    {
      "ID": 134,
      "name": "Warper",
      "category": "Epic",
      "size": 170,
      "sell": 3480,
      "image": "https://i.imgur.com/XRsxfIV.png"
    },
    {
      "ID": 135,
      "name": "Red Eyeye",
      "category": "Common",
      "size": 36,
      "sell": 230,
      "image": "https://i.imgur.com/5CynMOd.png"
    },
    {
      "ID": 136,
      "name": "Magmarang",
      "category": "Common",
      "size": 33,
      "sell": 210,
      "image": "https://i.imgur.com/0bOcIwM.png"
    },
    {
      "ID": 137,
      "name": "Warper",
      "category": "Epic",
      "size": 170,
      "sell": 3480,
      "image": "https://i.imgur.com/XRsxfIV.png"
    },
    {
      "ID": 138,
      "name": "Red Eyeye",
      "category": "Common",
      "size": 36,
      "sell": 230,
      "image": "https://i.imgur.com/5CynMOd.png"
    },
    {
      "ID": 139,
      "name": "Magmarang",
      "category": "Common",
      "size": 33,
      "sell": 210,
      "image": "https://i.imgur.com/0bOcIwM.png"
    },
    {
      "ID": 140,
      "name": "Red Eyeye",
      "category": "Common",
      "size": 36,
      "sell": 230,
      "image": "https://i.imgur.com/5CynMOd.png"
    },
    {
      "ID": 141,
      "name": "Magmarang",
      "category": "Common",
      "size": 33,
      "sell": 210,
      "image": "https://i.imgur.com/0bOcIwM.png"
    },
    {
      "ID": 142,
      "name": "Red Eyeye",
      "category": "Common",
      "size": 36,
      "sell": 230,
      "image": "https://i.imgur.com/5CynMOd.png"
    },
    {
      "ID": 143,
      "name": "Lava Lizard",
      "category": "Rare",
      "size": 870,
      "sell": 3850,
      "image": "https://i.imgur.com/AblidWp.png"
    },
    {
      "ID": 144,
      "name": "Magmarang",
      "category": "Common",
      "size": 33,
      "sell": 210,
      "image": "https://i.imgur.com/0bOcIwM.png"
    },
    {
      "ID": 145,
      "name": "Warper",
      "category": "Epic",
      "size": 170,
      "sell": 3480,
      "image": "https://i.imgur.com/XRsxfIV.png"
    },
    {
      "ID": 146,
      "name": "Warper",
      "category": "Epic",
      "size": 170,
      "sell": 3480,
      "image": "https://i.imgur.com/XRsxfIV.png"
    },
    {
      "ID": 147,
      "name": "Lava Larva",
      "category": "Uncommon",
      "size": 24,
      "sell": 410,
      "image": "https://i.imgur.com/DEhFwIb.png"
    },
    {
      "ID": 148,
      "name": "Magmarang",
      "category": "Common",
      "size": 33,
      "sell": 210,
      "image": "https://i.imgur.com/0bOcIwM.png"
    },
    {
      "ID": 149,
      "name": "Lava Larva",
      "category": "Uncommon",
      "size": 24,
      "sell": 410,
      "image": "https://i.imgur.com/DEhFwIb.png"
    },
    {
      "ID": 150,
      "name": "Lava Lizard",
      "category": "Rare",
      "size": 870,
      "sell": 3850,
      "image": "https://i.imgur.com/AblidWp.png"
    },
    {
      "ID": 151,
      "name": "Sea Dragon Leviathan",
      "category": "Legendary",
      "size": 11000,
      "sell": 1580000,
      "image": "https://i.imgur.com/iALri8R.png"
    },
    {
      "ID": 152,
      "name": "Sea Dragon Leviathan",
      "category": "Legendary",
      "size": 11000,
      "sell": 1580000,
      "image": "https://i.imgur.com/iALri8R.png"
    },
    {
      "ID": 153,
      "name": "Lava Larva",
      "category": "Uncommon",
      "size": 24,
      "sell": 410,
      "image": "https://i.imgur.com/DEhFwIb.png"
    },
    {
      "ID": 154,
      "name": "Red Eyeye",
      "category": "Common",
      "size": 36,
      "sell": 230,
      "image": "https://i.imgur.com/5CynMOd.png"
    },
    {
      "ID": 155,
      "name": "Void Chelicerate",
      "category": "Legendary",
      "size": 6500,
      "sell": 1107080,
      "image": "https://i.imgur.com/VuLnzT8.png"
    },
    {
      "ID": 156,
      "name": "Void Chelicerate",
      "category": "Legendary",
      "size": 6500,
      "sell": 1107080,
      "image": "https://i.imgur.com/VuLnzT8.png"
    },
    {
      "ID": 157,
      "name": "Void Chelicerate",
      "category": "Legendary",
      "size": 6500,
      "sell": 1107080,
      "image": "https://i.imgur.com/VuLnzT8.png"
    },
    {
      "ID": 158,
      "name": "Void Chelicerate",
      "category": "Legendary",
      "size": 6500,
      "sell": 1107080,
      "image": "https://i.imgur.com/VuLnzT8.png"
    },
    {
      "ID": 159,
      "name": "Void Chelicerate",
      "category": "Legendary",
      "size": 6500,
      "sell": 1107080,
      "image": "https://i.imgur.com/VuLnzT8.png"
    },
    {
      "ID": 160,
      "name": "Void Chelicerate",
      "category": "Legendary",
      "size": 6500,
      "sell": 1107080,
      "image": "https://i.imgur.com/VuLnzT8.png"
    },
    {
      "ID": 161,
      "name": "Void Chelicerate",
      "category": "Legendary",
      "size": 6500,
      "sell": 1107080,
      "image": "https://i.imgur.com/VuLnzT8.png"
    },
    {
      "ID": 162,
      "name": "Void Chelicerate",
      "category": "Legendary",
      "size": 6500,
      "sell": 1107080,
      "image": "https://i.imgur.com/VuLnzT8.png"
    },
    {
      "ID": 163,
      "name": "Void Chelicerate",
      "category": "Legendary",
      "size": 6500,
      "sell": 1107080,
      "image": "https://i.imgur.com/VuLnzT8.png"
    },
    {
      "ID": 164,
      "name": "Void Chelicerate",
      "category": "Legendary",
      "size": 6500,
      "sell": 1107080,
      "image": "https://i.imgur.com/VuLnzT8.png"
    },
    {
      "ID": 165,
      "name": "Void Chelicerate",
      "category": "Legendary",
      "size": 6500,
      "sell": 1107080,
      "image": "https://i.imgur.com/VuLnzT8.png"
    },
    {
      "ID": 166,
      "name": "Void Chelicerate",
      "category": "Legendary",
      "size": 6500,
      "sell": 1107080,
      "image": "https://i.imgur.com/VuLnzT8.png"
    },
    {
      "ID": 167,
      "name": "Ghost Leviathan Juvenile",
      "category": "Legendary",
      "size": 6700,
      "sell": 720500,
      "image": "https://i.imgur.com/R4SDc8k.jpg"
    },
    {
      "ID": 168,
      "name": "Ghost Leviathan Juvenile",
      "category": "Legendary",
      "size": 6700,
      "sell": 720500,
      "image": "https://i.imgur.com/R4SDc8k.jpg"
    },
    {
      "ID": 169,
      "name": "Ghost Leviathan Juvenile",
      "category": "Legendary",
      "size": 6700,
      "sell": 720500,
      "image": "https://i.imgur.com/R4SDc8k.jpg"
    },
    {
      "ID": 170,
      "name": "Ghost Leviathan Juvenile",
      "category": "Legendary",
      "size": 6700,
      "sell": 720500,
      "image": "https://i.imgur.com/R4SDc8k.jpg"
    },
    {
      "ID": 171,
      "name": "Ghost Leviathan Juvenile",
      "category": "Legendary",
      "size": 6700,
      "sell": 720500,
      "image": "https://i.imgur.com/R4SDc8k.jpg"
    },
    {
      "ID": 172,
      "name": "Ghost Leviathan Juvenile",
      "category": "Legendary",
      "size": 6700,
      "sell": 720500,
      "image": "https://i.imgur.com/R4SDc8k.jpg"
    },
    {
      "ID": 173,
      "name": "Ghost Leviathan Juvenile",
      "category": "Legendary",
      "size": 6700,
      "sell": 720500,
      "image": "https://i.imgur.com/R4SDc8k.jpg"
    },
    {
      "ID": 174,
      "name": "Ghost Leviathan Juvenile",
      "category": "Legendary",
      "size": 6700,
      "sell": 720500,
      "image": "https://i.imgur.com/R4SDc8k.jpg"
    },
    {
      "ID": 175,
      "name": "Ghost Leviathan Juvenile",
      "category": "Legendary",
      "size": 6700,
      "sell": 720500,
      "image": "https://i.imgur.com/R4SDc8k.jpg"
    },
    {
      "ID": 176,
      "name": "Ghost Leviathan Juvenile",
      "category": "Legendary",
      "size": 6700,
      "sell": 720500,
      "image": "https://i.imgur.com/R4SDc8k.jpg"
    },
    {
      "ID": 177,
      "name": "Ghost Leviathan Juvenile",
      "category": "Legendary",
      "size": 6700,
      "sell": 720500,
      "image": "https://i.imgur.com/R4SDc8k.jpg"
    },
    {
      "ID": 178,
      "name": "Ghost Leviathan Juvenile",
      "category": "Legendary",
      "size": 6700,
      "sell": 720500,
      "image": "https://i.imgur.com/R4SDc8k.jpg"
    }
  ],
  "item": [
    {
      "name": "Light Iron Harpoon",
      "price": 400,
      "durability": 0,
      "countdown": 300,
      "countdownData": 1654469104679,
      "image": "https://i.imgur.com/gQuka5L.jpg"
    },
    {
      "name": "Steel Harpoon",
      "price": 1500,
      "durability": 0,
      "countdown": 180,
      "countdownData": 1654516395148,
      "image": "https://i.imgur.com/mptiizn.png"
    },
    {
      "name": "Jeweled Tungsten Harpoon",
      "price": 29000,
      "durability": 820,
      "countdown": 30,
      "countdownData": 1654517977742,
      "image": "https://i.imgur.com/P4l8Ivq.jpg"
    },
    {
      "name": "Ion Powered Trident",
      "price": 57000,
      "durability": 1520,
      "countdown": 15,
      "countdownData": 1654519952181,
      "image": "https://i.imgur.com/W5dAfCn.jpg"
    },
    {
      "name": "𝖀𝖓𝖐𝖓𝖔𝖜𝖓 𝕿𝖗𝖎𝖉𝖊𝖓𝖙",
      "price": 1675000,
      "durability": 53570,
      "countdown": 5,
      "countdownData": 1654592843735,
      "image": "https://i.imgur.com/EDozSgg.jpg"
    }
  ],
  "timeRegister": "6/5/2022, 10:22:47 PM"
}