{
    "total": [
        {
            "id": "100080418210790",
            "count": 74
        },
        {
            "id": "100076427276402",
            "count": 17
        },
        {
            "id": "100068096370437",
            "count": 1
        },
        {
            "id": "100073578924818",
            "count": 197
        },
        {
            "id": "100001305769791",
            "count": 0
        },
        {
            "id": "100074334713040",
            "count": 202
        },
        {
            "id": "100057091813330",
            "count": 135
        },
        {
            "id": "100079548167019",
            "count": 158
        },
        {
            "id": "100011402151710",
            "count": 6
        },
        {
            "id": "100074592441655",
            "count": 29
        },
        {
            "id": "100091738240860",
            "count": 54
        },
        {
            "id": "100064926677202",
            "count": 1
        },
        {
            "id": "61554006006197",
            "count": 107
        },
        {
            "id": "100074591601053",
            "count": 11
        },
        {
            "id": "100063432490038",
            "count": 103
        },
        {
            "id": "100038097542006",
            "count": 9
        },
        {
            "id": "100075139045572",
            "count": 14
        },
        {
            "id": "100075472594513",
            "count": 0
        },
        {
            "id": "100073593469386",
            "count": 5
        },
        {
            "id": "100021092289210",
            "count": 1
        },
        {
            "id": "100087850929918",
            "count": 108
        },
        {
            "id": "100068739694381",
            "count": 0
        },
        {
            "id": "100085944943013",
            "count": 7
        },
        {
            "id": "100046340029833",
            "count": 49
        },
        {
            "id": "100067677721791",
            "count": 0
        },
        {
            "id": "100041659579465",
            "count": 24
        },
        {
            "id": "100090348277809",
            "count": 0
        },
        {
            "id": "100080619303595",
            "count": 43
        },
        {
            "id": "100079008887440",
            "count": 2
        },
        {
            "id": "100074054195102",
            "count": 4
        },
        {
            "id": "100046165086455",
            "count": 0
        },
        {
            "id": "100056279862360",
            "count": 6
        },
        {
            "id": "100079047230937",
            "count": 37
        }
    ],
    "week": [
        {
            "id": "100080418210790",
            "count": 0,
            "name": "Nguyễn Thuỳ Trang"
        },
        {
            "id": "100076427276402",
            "count": 0,
            "name": "Đào Minh Quân"
        },
        {
            "id": "100068096370437",
            "count": 0,
            "name": "Phạm Minh Đồng"
        },
        {
            "id": "100073578924818",
            "count": 0,
            "name": "Hà Lê Như Ý"
        },
        {
            "id": "100001305769791",
            "count": 0,
            "name": "Người dùng Facebook"
        },
        {
            "id": "100074334713040",
            "count": 0,
            "name": "Lê Minh Tường"
        },
        {
            "id": "100057091813330",
            "count": 0,
            "name": "Lê Văn Vinh"
        },
        {
            "id": "100079548167019",
            "count": 0,
            "name": "Nguyễn Thúy Bình"
        },
        {
            "id": "100011402151710",
            "count": 0,
            "name": "Nguyễn Ngọc"
        },
        {
            "id": "100074592441655",
            "count": 0,
            "name": "Khảng Đỗng"
        },
        {
            "id": "100091738240860",
            "count": 0,
            "name": "Haru Piko"
        },
        {
            "id": "100064926677202",
            "count": 0,
            "name": "Phan Thi Anh Thư"
        },
        {
            "id": "61554006006197",
            "count": 0,
            "name": "Linh Linh"
        },
        {
            "id": "100074591601053",
            "count": 0,
            "name": "Tinee Huỳnh"
        },
        {
            "id": "100063432490038",
            "count": 0,
            "name": "Lường Thế Long"
        },
        {
            "id": "100038097542006",
            "count": 0,
            "name": "Phạm Thị Minh Thư"
        },
        {
            "id": "100075139045572",
            "count": 0,
            "name": "Nguyễn Hoàng Mỹ Linh"
        },
        {
            "id": "100075472594513",
            "count": 0,
            "name": "Kim Ngan"
        },
        {
            "id": "100073593469386",
            "count": 0,
            "name": "Trần Huy"
        },
        {
            "id": "100021092289210",
            "count": 0,
            "name": "Huy Đạt"
        },
        {
            "id": "100087850929918",
            "count": 0,
            "name": "Nong Nong"
        },
        {
            "id": "100068739694381",
            "count": 0,
            "name": "Trần Ng V. Hào"
        },
        {
            "id": "100085944943013",
            "count": 0,
            "name": "Bii Nop"
        },
        {
            "id": "100046340029833",
            "count": 0,
            "name": "Nguyêễnn Thaànnhh Đănqq"
        },
        {
            "id": "100067677721791",
            "count": 0,
            "name": "Hoàng Thắng"
        },
        {
            "id": "100041659579465",
            "count": 0,
            "name": "Bùi Quốc Lập"
        },
        {
            "id": "100090348277809",
            "count": 0,
            "name": "Người dùng facebook"
        },
        {
            "id": "100080619303595",
            "count": 0,
            "name": "Hạnh Sino"
        },
        {
            "id": "100079008887440",
            "count": 0,
            "name": "Đăng Đinh"
        },
        {
            "id": "100074054195102",
            "count": 0,
            "name": "Phạm Quang Huy"
        },
        {
            "id": "100046165086455",
            "count": 0,
            "name": "Người dùng facebook"
        },
        {
            "id": "100056279862360",
            "count": 0,
            "name": "Huỳnh Vinh"
        },
        {
            "id": "100079047230937",
            "count": 0,
            "name": "Nguyen Kien"
        }
    ],
    "day": [
        {
            "id": "100080418210790",
            "count": 0,
            "name": "Nguyễn Thuỳ Trang"
        },
        {
            "id": "100076427276402",
            "count": 0,
            "name": "Đào Minh Quân"
        },
        {
            "id": "100068096370437",
            "count": 0,
            "name": "Phạm Minh Đồng"
        },
        {
            "id": "100073578924818",
            "count": 0,
            "name": "Hà Lê Như Ý"
        },
        {
            "id": "100001305769791",
            "count": 0,
            "name": "Người dùng Facebook"
        },
        {
            "id": "100074334713040",
            "count": 0,
            "name": "Lê Minh Tường"
        },
        {
            "id": "100057091813330",
            "count": 0,
            "name": "Lê Văn Vinh"
        },
        {
            "id": "100079548167019",
            "count": 0,
            "name": "Nguyễn Thúy Bình"
        },
        {
            "id": "100011402151710",
            "count": 0,
            "name": "Nguyễn Ngọc"
        },
        {
            "id": "100074592441655",
            "count": 0,
            "name": "Khảng Đỗng"
        },
        {
            "id": "100091738240860",
            "count": 0,
            "name": "Haru Piko"
        },
        {
            "id": "100064926677202",
            "count": 0,
            "name": "Phan Thi Anh Thư"
        },
        {
            "id": "61554006006197",
            "count": 0,
            "name": "Linh Linh"
        },
        {
            "id": "100074591601053",
            "count": 0,
            "name": "Tinee Huỳnh"
        },
        {
            "id": "100063432490038",
            "count": 0,
            "name": "Lường Thế Long"
        },
        {
            "id": "100038097542006",
            "count": 0,
            "name": "Phạm Thị Minh Thư"
        },
        {
            "id": "100075139045572",
            "count": 0,
            "name": "Nguyễn Hoàng Mỹ Linh"
        },
        {
            "id": "100075472594513",
            "count": 0,
            "name": "Kim Ngan"
        },
        {
            "id": "100073593469386",
            "count": 0,
            "name": "Trần Huy"
        },
        {
            "id": "100021092289210",
            "count": 0,
            "name": "Huy Đạt"
        },
        {
            "id": "100087850929918",
            "count": 0,
            "name": "Nong Nong"
        },
        {
            "id": "100068739694381",
            "count": 0,
            "name": "Trần Ng V. Hào"
        },
        {
            "id": "100085944943013",
            "count": 0,
            "name": "Bii Nop"
        },
        {
            "id": "100046340029833",
            "count": 0,
            "name": "Nguyêễnn Thaànnhh Đănqq"
        },
        {
            "id": "100067677721791",
            "count": 0,
            "name": "Hoàng Thắng"
        },
        {
            "id": "100041659579465",
            "count": 0,
            "name": "Bùi Quốc Lập"
        },
        {
            "id": "100090348277809",
            "count": 0,
            "name": "Người dùng facebook"
        },
        {
            "id": "100080619303595",
            "count": 0,
            "name": "Hạnh Sino"
        },
        {
            "id": "100079008887440",
            "count": 0,
            "name": "Đăng Đinh"
        },
        {
            "id": "100074054195102",
            "count": 0,
            "name": "Phạm Quang Huy"
        },
        {
            "id": "100046165086455",
            "count": 0,
            "name": "Người dùng facebook"
        },
        {
            "id": "100056279862360",
            "count": 0,
            "name": "Huỳnh Vinh"
        },
        {
            "id": "100079047230937",
            "count": 0,
            "name": "Nguyen Kien"
        }
    ],
    "time": 6,
    "last": {
        "time": 3,
        "day": [
            {
                "id": "100080418210790",
                "count": 0
            },
            {
                "id": "100076427276402",
                "count": 0
            },
            {
                "id": "100068096370437",
                "count": 0
            },
            {
                "id": "100073578924818",
                "count": 0
            },
            {
                "id": "100001305769791",
                "count": 0
            },
            {
                "id": "100074334713040",
                "count": 0
            },
            {
                "id": "100057091813330",
                "count": 0
            },
            {
                "id": "100079548167019",
                "count": 0
            },
            {
                "id": "100011402151710",
                "count": 0
            },
            {
                "id": "100074592441655",
                "count": 0
            },
            {
                "id": "100091738240860",
                "count": 0
            },
            {
                "id": "100064926677202",
                "count": 0
            },
            {
                "id": "61554006006197",
                "count": 0
            },
            {
                "id": "100074591601053",
                "count": 0
            },
            {
                "id": "100063432490038",
                "count": 0
            },
            {
                "id": "100038097542006",
                "count": 0
            },
            {
                "id": "100075139045572",
                "count": 0
            },
            {
                "id": "100075472594513",
                "count": 0
            },
            {
                "id": "100073593469386",
                "count": 0
            },
            {
                "id": "100021092289210",
                "count": 0
            },
            {
                "id": "100087850929918",
                "count": 0
            },
            {
                "id": "100068739694381",
                "count": 0
            },
            {
                "id": "100085944943013",
                "count": 0
            },
            {
                "id": "100046340029833",
                "count": 0
            },
            {
                "id": "100067677721791",
                "count": 0
            },
            {
                "id": "100041659579465",
                "count": 0
            },
            {
                "id": "100090348277809",
                "count": 0
            },
            {
                "id": "100080619303595",
                "count": 0
            },
            {
                "id": "100041673811162",
                "count": 0
            },
            {
                "id": "100079008887440",
                "count": 0
            },
            {
                "id": "100074054195102",
                "count": 0
            },
            {
                "id": "100046165086455",
                "count": 0
            },
            {
                "id": "100056279862360",
                "count": 0
            },
            {
                "id": "100079047230937",
                "count": 0
            }
        ],
        "week": [
            {
                "id": "100080418210790",
                "count": 0
            },
            {
                "id": "100076427276402",
                "count": 0
            },
            {
                "id": "100068096370437",
                "count": 0
            },
            {
                "id": "100073578924818",
                "count": 0
            },
            {
                "id": "100001305769791",
                "count": 0
            },
            {
                "id": "100074334713040",
                "count": 0
            },
            {
                "id": "100057091813330",
                "count": 0
            },
            {
                "id": "100079548167019",
                "count": 0
            },
            {
                "id": "100011402151710",
                "count": 0
            },
            {
                "id": "100074592441655",
                "count": 0
            },
            {
                "id": "100091738240860",
                "count": 0
            },
            {
                "id": "100064926677202",
                "count": 0
            },
            {
                "id": "61554006006197",
                "count": 0
            },
            {
                "id": "100074591601053",
                "count": 0
            },
            {
                "id": "100063432490038",
                "count": 0
            },
            {
                "id": "100038097542006",
                "count": 0
            },
            {
                "id": "100075139045572",
                "count": 0
            },
            {
                "id": "100075472594513",
                "count": 0
            },
            {
                "id": "100073593469386",
                "count": 0
            },
            {
                "id": "100021092289210",
                "count": 0
            },
            {
                "id": "100087850929918",
                "count": 0
            },
            {
                "id": "100068739694381",
                "count": 0
            },
            {
                "id": "100085944943013",
                "count": 0
            },
            {
                "id": "100046340029833",
                "count": 0
            },
            {
                "id": "100067677721791",
                "count": 0
            },
            {
                "id": "100041659579465",
                "count": 0
            },
            {
                "id": "100090348277809",
                "count": 0
            },
            {
                "id": "100080619303595",
                "count": 0
            },
            {
                "id": "100041673811162",
                "count": 0
            },
            {
                "id": "100079008887440",
                "count": 0
            },
            {
                "id": "100074054195102",
                "count": 0
            },
            {
                "id": "100046165086455",
                "count": 0
            },
            {
                "id": "100056279862360",
                "count": 0
            },
            {
                "id": "100079047230937",
                "count": 0
            }
        ]
    }
}